{
  "timeBins":[
    {
      "data":[
        {"i": "重庆", "e": "英国","c":"pos","v": 70},
        {"i": "广州", "e": "日本","c":"neg","v": 30},
        {"i": "南宁", "e": "加拿大","c":"pos","v": 80},
        {"i": "南宁", "e": "美国","c":"neu","v": 100},
        {"i": "南宁", "e": "澳大利亚","c":"pos","v": 95},
        {"i": "南宁", "e": "瑞士","c":"neg","v": 50}
      ],
      "t":2015
    },
    {
      "data":[
        {"i": "日本", "e": "南宁","c":"neg","v": 50},
        {"i": "美国", "e": "日本","c":"pos","v": 100},
        {"i": "澳大利亚", "e": "加拿大","c":"neg","v": 40},
        {"i": "南宁", "e": "英国","c":"pos","v": 30},
        {"i": "日本", "e": "澳大利亚","c":"neu","v": 80},
        {"i": "南宁", "e": "日本","c":"pos","v": 10}
      ],
      "t":2016
    },
    {
      "data":[
        {"i": "重庆", "e": "英国","c":"pos","v": 70},
        {"i": "广州", "e": "日本","c":"pos","v": 30},
        {"i": "南宁", "e": "加拿大","c":"neg","v": 80},
        {"i": "南宁", "e": "加拿大","c":"neu","v": 100},
        {"i": "南宁", "e": "澳大利亚","c":"neg","v": 95},
        {"i": "南宁", "e": "瑞士","c":"neu","v": 50}
      ],
      "t":2017
    },
    {
      "data":[
        {"i": "重庆", "e": "英国","c":"pos","v": 70},
        {"i": "广州", "e": "日本","c":"pos","v": 30},
        {"i": "南宁", "e": "加拿大","c":"pos","v": 80},
        {"i": "南宁", "e": "美国","c":"pos","v": 100},
        {"i": "南宁", "e": "澳大利亚","c":"pos","v": 95},
        {"i": "南宁", "e": "瑞士","c":"pos","v": 50}
      ],
      "t":2018
    },
    {
      "data":[
        {"i": "重庆", "e": "英国","c":"pos","v": 70},
        {"i": "广州", "e": "日本","c":"pos","v": 30},
        {"i": "南宁", "e": "加拿大","c":"pos","v": 80},
        {"i": "南宁", "e": "美国","c":"pos","v": 100},
        {"i": "南宁", "e": "澳大利亚","c":"pos","v": 95},
        {"i": "南宁", "e": "瑞士","c":"pos","v": 50}
      ],
      "t":2019
    }
  ]
}